{"expireTime":9007200871848627000,"key":"c0d7d245d9e23d15fb95ac7b39626616","val":{"name":"IMAGE_PROCESSING","inputPaths":["D:/Capsule Corp/BOILER PLATES/Gatsby/Themes/gatsby-theme-june/packages/gatsby-theme-june/src/images/hero_heavy.jpg"],"outputDir":"D:/Capsule Corp/BOILER PLATES/Gatsby/Themes/gatsby-theme-june/site/public/static/6f8d2da7f1f020128d0e57818a129494","args":{"isLazy":false,"operations":[{"outputPath":"2b8d7\\hero_heavy.webp","args":{"height":1000,"width":1500,"cropFocus":17,"toFormat":"webp","fit":"cover"}},{"outputPath":"48dc9\\hero_heavy.webp","args":{"height":2000,"width":3000,"cropFocus":17,"toFormat":"webp","fit":"cover"}},{"outputPath":"5de91\\hero_heavy.webp","args":{"height":4000,"width":6000,"cropFocus":17,"toFormat":"webp","fit":"cover"}}],"pluginOptions":{"base64Width":20,"forceBase64Format":"","useMozJpeg":false,"stripMetadata":true,"lazyImageGeneration":true,"defaultQuality":50,"failOnError":true,"plugins":[]}}}}